rd_jaour_bill_update/__init__.py
rd_jaour_bill_update/bill_main.py
rd_jaour_his/__init__.py
rd_jaour_his/jh_his.py
rdjaourhis-1.1.0.dist-info/METADATA
rdjaourhis-1.1.0.dist-info/WHEEL
rdjaourhis-1.1.0.dist-info/top_level.txt
rdjaourhis-1.1.0.dist-info/RECORD
