Metadata-Version: 2.1
Name: rdjaourhis
Version: 1.1.0
Summary: reshape data type in py language 
Home-page: http://www.reshapedata.com
Author: zhangchaoyang
Author-email: 764563896@qq.com
License: Apache License
Keywords: reshapedata,rdt,pyrdt
Platform: UNKNOWN
Requires-Python: >=3.6
Requires-Dist: requests
